thoth/analyzer/__init__.py
thoth/analyzer/cli.py
thoth/analyzer/command.py
thoth_analyzer-0.1.8.dist-info/DESCRIPTION.rst
thoth_analyzer-0.1.8.dist-info/METADATA
thoth_analyzer-0.1.8.dist-info/RECORD
thoth_analyzer-0.1.8.dist-info/WHEEL
thoth_analyzer-0.1.8.dist-info/metadata.json
thoth_analyzer-0.1.8.dist-info/top_level.txt
