Metadata-Version: 1.0
Name: thoth-analyzer
Version: 0.1.8
Summary: Analyzer library for project Thoht.
Home-page: UNKNOWN
Author: Fridolin Pokorny
Author-email: fridolin@redhat.com
License: GPLv3+
Platform: UNKNOWN
